src/recandle/__init__.py
src/recandle/re_candle.py
metafid-0.0.1.dist-info/METADATA
metafid-0.0.1.dist-info/WHEEL
metafid-0.0.1.dist-info/licenses/LICENSE
metafid-0.0.1.dist-info/RECORD
